config/.env
config/settings.py
talkative_server/README.md
talkative_server/__init__.py
talkative_server/__main__.py
talkative_server/cli.py
talkative_server/commands.py
talkative_server/contacts/commands.py
talkative_server/core.py
talkative_server/db.py
talkative_server/decorators.py
talkative_server/descriptors.py
talkative_server/docs/Makefile
talkative_server/docs/_build/doctrees/environment.pickle
talkative_server/docs/_build/doctrees/index.doctree
talkative_server/docs/_build/doctrees/server.doctree
talkative_server/docs/_build/doctrees/server.jim_mes.doctree
talkative_server/docs/_build/html/.buildinfo
talkative_server/docs/_build/html/_modules/cli.html
talkative_server/docs/_build/html/_modules/commands.html
talkative_server/docs/_build/html/_modules/core.html
talkative_server/docs/_build/html/_modules/db.html
talkative_server/docs/_build/html/_modules/decorators.html
talkative_server/docs/_build/html/_modules/descriptors.html
talkative_server/docs/_build/html/_modules/dis.html
talkative_server/docs/_build/html/_modules/errors.html
talkative_server/docs/_build/html/_modules/gui.html
talkative_server/docs/_build/html/_modules/index.html
talkative_server/docs/_build/html/_modules/jim_mes/convert.html
talkative_server/docs/_build/html/_modules/jim_mes/jim.html
talkative_server/docs/_build/html/_modules/metaclasses.html
talkative_server/docs/_build/html/_modules/sqlalchemy/orm/attributes.html
talkative_server/docs/_build/html/_sources/index.rst.txt
talkative_server/docs/_build/html/_sources/server.jim_mes.rst.txt
talkative_server/docs/_build/html/_sources/server.rst.txt
talkative_server/docs/_build/html/_static/_stemmer.js
talkative_server/docs/_build/html/_static/basic.css
talkative_server/docs/_build/html/_static/css/badge_only.css
talkative_server/docs/_build/html/_static/css/theme.css
talkative_server/docs/_build/html/_static/doctools.js
talkative_server/docs/_build/html/_static/documentation_options.js
talkative_server/docs/_build/html/_static/file.png
talkative_server-0.1.2.dist-info/WHEEL
talkative_server-0.1.2.dist-info/METADATA
talkative_server-0.1.2.dist-info/RECORD
