Metadata-Version: 2.1
Name: talkative-server
Version: 0.1.2
Summary: It is example project for study
Home-page: https://github.com/mom1/messager
Author: MaxST
Author-email: mstolpasov@gmail.com
Requires-Python: >=3.7,<4.0
Classifier: Programming Language :: Python :: 3
Classifier: Programming Language :: Python :: 3.7
Requires-Dist: dynaconf (>=2.0,<3.0)
Requires-Dist: passlib (>=1.7,<2.0)
Requires-Dist: pycryptodomex (>=3.8,<4.0)
Requires-Dist: pyqt5 (>=5.13,<6.0)
Requires-Dist: pyyaml (>=5.1,<6.0)
Requires-Dist: sqlalchemy (>=1.3,<2.0)
Requires-Dist: sqlalchemy-utils (>=0.34.1,<0.35.0)
Requires-Dist: tabulate (>=0.8.3,<0.9.0)
Project-URL: Repository, https://github.com/mom1/messager
